data_buyer_toolkit/ __init__.py
data_buyer_toolkit/README.md
data_buyer_toolkit/nlp_pipeline_with_smote.joblib
data_buyer_toolkit/toolkit.py
data_buyer_toolkit-0.1.8.dist-info/METADATA
data_buyer_toolkit-0.1.8.dist-info/WHEEL
data_buyer_toolkit-0.1.8.dist-info/top_level.txt
data_buyer_toolkit-0.1.8.dist-info/RECORD
